setup.cfg
setup.py
bin/eszcp-polling
zcp/__init__.py
zcp/ceilometer_client.py
zcp/exceptions.py
zcp/keystone_client.py
zcp/messaging.py
zcp/nova_client.py
zcp/utils.py
zcp/zabbix_handler.py
zcp.egg-info/PKG-INFO
zcp.egg-info/SOURCES.txt
zcp.egg-info/dependency_links.txt
zcp.egg-info/top_level.txt
zcp/cmd/__init__.py
zcp/cmd/proxy.py
zcp/common/__init__.py
zcp/common/conf.py
zcp/common/log.py
zcp/common/db/__init__.py
zcp/common/db/impl_mongo.py
zcp/common/db/models.py
zcp/common/db/pymongo_utils.py
zcp/task/__init__.py
zcp/task/keystone_handler.py
zcp/task/nova_handler.py
zcp/task/polling/__init__.py
zcp/task/polling/base_handler.py
zcp/task/polling/ceilometer_handler.py
zcp/task/polling/mongodb_handler.py