Metadata-Version: 1.1
Name: zcp
Version: 1.0.1
Summary: A Timer task for polling ceilometer metrics into zabbix
Home-page: https://github.com/apolloliu/ZCP
Author: hanxi.liu
Author-email: apolloliuhx@gmail.com
License: UNKNOWN
Platform: UNKNOWN
Classifier: Intended Audience :: Information Technology
Classifier: Intended Audience :: System Administrators
Classifier: License :: OSI Approved :: Apache Software License
Classifier: Operating System :: POSIX :: Linux
Classifier: Programming Language :: Python
Classifier: Programming Language :: Python :: 2
Classifier: Programming Language :: Python :: 2.7
Classifier: Programming Language :: Python :: 3
Classifier: Programming Language :: Python :: 3.5
